copier_uvscaffoldingtest/UvScaffolding_sample_file.py
copier_uvscaffoldingtest/__init__.py
copier_uvscaffoldingtest/py.typed
copier_uvscaffoldingtest-0.1.3.dist-info/METADATA
copier_uvscaffoldingtest-0.1.3.dist-info/WHEEL
copier_uvscaffoldingtest-0.1.3.dist-info/licenses/LICENSE
copier_uvscaffoldingtest-0.1.3.dist-info/RECORD
