Metadata-Version: 2.4
Name: copier-uvscaffoldingtest
Version: 0.1.3
Summary: Add your description here
Project-URL: Homepage, https://github.com/davidbrownell/copier-UvScaffoldingTest
Project-URL: Documentation, https://github.com/davidbrownell/copier-UvScaffoldingTest
Project-URL: Repository, https://github.com/davidbrownell/copier-UvScaffoldingTest
Author-email: David Brownell <db@davidbrownell.com>
License: MIT
License-File: LICENSE
Classifier: Operating System :: MacOS
Classifier: Operating System :: Microsoft :: Windows
Classifier: Operating System :: POSIX :: Linux
Classifier: Programming Language :: Python
Classifier: Programming Language :: Python :: 3.10
Classifier: Programming Language :: Python :: 3.11
Classifier: Programming Language :: Python :: 3.12
Classifier: Programming Language :: Python :: 3.13
Requires-Python: >=3.10
